mtg_pynance-0.1.7.3.dist-info/METADATA
mtg_pynance-0.1.7.3.dist-info/WHEEL
mtg_pynance-0.1.7.3.dist-info/entry_points.txt
mtg_pynance-0.1.7.3.dist-info/licenses/LICENSE
mtg_pynance/__init__.py
mtg_pynance/analysis.py
mtg_pynance/collection.py
mtg_pynance/config.py
mtg_pynance/core.py
mtg_pynance/logger.py
mtg_pynance/retrieval.py
mtg_pynance-0.1.7.3.dist-info/RECORD
