Metadata-Version: 2.1
Name: mtg_pynance
Version: 0.1.7.3
Summary: Package of tools to record, store, and analyze your Magic the Gathering collection.
Author-Email: Zach Serikow <76140451+sigmanotation@users.noreply.github.com>
License: GPL-3.0-only
Requires-Python: >=3.13
Requires-Dist: requests>=2.32.5
Requires-Dist: pathlib>=1.0.1
Requires-Dist: datetime>=5.5
Requires-Dist: polars>=1.35.1
Requires-Dist: numpy>=2.3.4
Requires-Dist: tqdm>=4.67.1
